[
  {
    "rank": 1,
    "team_key": "398.l.17906.t.3",
    "team_name": "JudgeJoey&Execution",
    "manager": "Tyler",
    "wins": 6,
    "losses": 1,
    "ties": 0,
    "win_pct": 0.857,
    "points_for": 2179.08,
    "points_against": 1616.58
  },
  {
    "rank": 2,
    "team_key": "398.l.17906.t.7",
    "team_name": "Finding Nimmo",
    "manager": "Red",
    "wins": 7,
    "losses": 0,
    "ties": 0,
    "win_pct": 1.0,
    "points_for": 1946.59,
    "points_against": 1425.24
  },
  {
    "rank": 3,
    "team_key": "398.l.17906.t.4",
    "team_name": "Catchers are a Myth",
    "manager": "Coleman",
    "wins": 6,
    "losses": 1,
    "ties": 0,
    "win_pct": 0.857,
    "points_for": 2229.75,
    "points_against": 1856.33
  },
  {
    "rank": 4,
    "team_key": "398.l.17906.t.11",
    "team_name": "Matt Chapman Stan",
    "manager": "Robert",
    "wins": 5,
    "losses": 2,
    "ties": 0,
    "win_pct": 0.714,
    "points_for": 1782.17,
    "points_against": 1735.25
  },
  {
    "rank": 5,
    "team_key": "398.l.17906.t.1",
    "team_name": "Shrimp Fried Bryce",
    "manager": "Josh",
    "wins": 3,
    "losses": 4,
    "ties": 0,
    "win_pct": 0.429,
    "points_for": 1772.16,
    "points_against": 1737.26
  },
  {
    "rank": 6,
    "team_key": "398.l.17906.t.2",
    "team_name": "Arizona Diamondsacks",
    "manager": "Josh",
    "wins": 2,
    "losses": 5,
    "ties": 0,
    "win_pct": 0.286,
    "points_for": 1665.33,
    "points_against": 1688.3400000000001
  },
  {
    "rank": 7,
    "team_key": "398.l.17906.t.5",
    "team_name": "Cole World",
    "manager": "Ryan",
    "wins": 3,
    "losses": 4,
    "ties": 0,
    "win_pct": 0.429,
    "points_for": 1903.26,
    "points_against": 1820.0
  },
  {
    "rank": 8,
    "team_key": "398.l.17906.t.9",
    "team_name": "Team Beer",
    "manager": "Rich",
    "wins": 4,
    "losses": 3,
    "ties": 0,
    "win_pct": 0.571,
    "points_for": 1424.4,
    "points_against": 1475.3400000000001
  },
  {
    "rank": 9,
    "team_key": "398.l.17906.t.8",
    "team_name": "All Hitting no Pitch",
    "manager": "dylan",
    "wins": 2,
    "losses": 5,
    "ties": 0,
    "win_pct": 0.286,
    "points_for": 1339.41,
    "points_against": 1422.25
  },
  {
    "rank": 10,
    "team_key": "398.l.17906.t.10",
    "team_name": "The Dali Lama",
    "manager": "JOHN",
    "wins": 2,
    "losses": 5,
    "ties": 0,
    "win_pct": 0.286,
    "points_for": 1206.76,
    "points_against": 1666.0799999999997
  },
  {
    "rank": 11,
    "team_key": "398.l.17906.t.6",
    "team_name": "GerritColeIsAYankee",
    "manager": "Riley",
    "wins": 1,
    "losses": 6,
    "ties": 0,
    "win_pct": 0.143,
    "points_for": 1265.25,
    "points_against": 1647.4999999999998
  },
  {
    "rank": 12,
    "team_key": "398.l.17906.t.12",
    "team_name": "Believe the Hype",
    "manager": "Logan",
    "wins": 1,
    "losses": 6,
    "ties": 0,
    "win_pct": 0.143,
    "points_for": 1140.59,
    "points_against": 1764.5800000000002
  }
]